spin_sdk/__init__.py
spin_sdk/componentize-py.toml
spin_sdk/key_value.py
spin_sdk/llm.py
spin_sdk/mqtt.py
spin_sdk/mysql.py
spin_sdk/postgres.py
spin_sdk/py.typed
spin_sdk/redis.py
spin_sdk/sqlite.py
spin_sdk/variables.py
spin_sdk/http/__init__.py
spin_sdk/http/poll_loop.py
spin_sdk/wit/__init__.py
spin_sdk/wit/key-value.wit
spin_sdk/wit/llm.wit
spin_sdk/wit/mqtt.wit
spin_sdk/wit/mysql.wit
spin_sdk/wit/postgres.wit
spin_sdk/wit/rdbms-types.wit
spin_sdk/wit/redis.wit
spin_sdk/wit/spin.wit
spin_sdk/wit/sqlite.wit
spin_sdk/wit/types.py
spin_sdk/wit/variables.wit
spin_sdk/wit/deps/cli/command.wit
spin_sdk/wit/deps/cli/environment.wit
spin_sdk/wit/deps/cli/exit.wit
spin_sdk/wit/deps/cli/imports.wit
spin_sdk/wit/deps/cli/run.wit
spin_sdk/wit/deps/cli/stdio.wit
spin_sdk/wit/deps/cli/terminal.wit
spin_sdk/wit/deps/clocks/monotonic-clock.wit
spin_sdk/wit/deps/clocks/wall-clock.wit
spin_sdk/wit/deps/clocks/world.wit
spin_sdk/wit/deps/filesystem/preopens.wit
spin_sdk/wit/deps/filesystem/types.wit
spin_sdk/wit/deps/filesystem/world.wit
spin_sdk/wit/deps/http/handler.wit
spin_sdk/wit/deps/http/proxy.wit
spin_sdk/wit/deps/http/types.wit
spin_sdk/wit/deps/io/error.wit
spin_sdk/wit/deps/io/poll.wit
spin_sdk/wit/deps/io/streams.wit
spin_sdk/wit/deps/io/world.wit
spin_sdk/wit/deps/keyvalue-2024-10-17/atomic.wit
spin_sdk/wit/deps/keyvalue-2024-10-17/batch.wit
spin_sdk/wit/deps/keyvalue-2024-10-17/store.wit
spin_sdk/wit/deps/keyvalue-2024-10-17/watch.wit
spin_sdk/wit/deps/keyvalue-2024-10-17/world.wit
spin_sdk/wit/deps/random/insecure-seed.wit
spin_sdk/wit/deps/random/insecure.wit
spin_sdk/wit/deps/random/random.wit
spin_sdk/wit/deps/random/world.wit
spin_sdk/wit/deps/sockets/instance-network.wit
spin_sdk/wit/deps/sockets/ip-name-lookup.wit
spin_sdk/wit/deps/sockets/network.wit
spin_sdk/wit/deps/sockets/tcp-create-socket.wit
spin_sdk/wit/deps/sockets/tcp.wit
spin_sdk/wit/deps/sockets/udp-create-socket.wit
spin_sdk/wit/deps/sockets/udp.wit
spin_sdk/wit/deps/sockets/world.wit
spin_sdk-3.3.0.dist-info/LICENSE
spin_sdk-3.3.0.dist-info/METADATA
spin_sdk-3.3.0.dist-info/WHEEL
spin_sdk-3.3.0.dist-info/top_level.txt
spin_sdk-3.3.0.dist-info/RECORD
