Metadata-Version: 2.1
Name: spin-sdk
Version: 3.3.0
Summary: Experimental SDK for Spin and Componentize-Py
Author-email: Fermyon Engineering <engineering@fermyon.com>
Maintainer-email: Fermyon Engineering <engineering@fermyon.com>
License:                               Apache License
Project-URL: repository, https://github.com/fermyon/spin-python-sdk
Project-URL: documentation, https://fermyon.github.io/spin-python-sdk
Keywords: webassembly,wasm,component,spin
License-File: LICENSE
